shapefile_to_sqlite/__init__.py
shapefile_to_sqlite/cli.py
shapefile_to_sqlite/utils.py
shapefile_to_sqlite-0.4.2.dist-info/LICENSE
shapefile_to_sqlite-0.4.2.dist-info/METADATA
shapefile_to_sqlite-0.4.2.dist-info/WHEEL
shapefile_to_sqlite-0.4.2.dist-info/entry_points.txt
shapefile_to_sqlite-0.4.2.dist-info/top_level.txt
shapefile_to_sqlite-0.4.2.dist-info/RECORD
