Metadata-Version: 2.1
Name: shapefile-to-sqlite
Version: 0.4.2
Summary: Load shapefiles into a SQLite (optionally SpatiaLite) database
Home-page: https://github.com/simonw/shapefile-to-sqlite
Author: Simon Willison
License: Apache License, Version 2.0
Project-URL: Issues, https://github.com/simonw/shapefile-to-sqlite/issues
Project-URL: CI, https://github.com/simonw/shapefile-to-sqlite/actions
Project-URL: Changelog, https://github.com/simonw/shapefile-to-sqlite/releases
License-File: LICENSE
Requires-Dist: sqlite-utils (>=2.2)
Requires-Dist: Shapely
Requires-Dist: Fiona
Requires-Dist: pyproj
Provides-Extra: test
Requires-Dist: pytest ; extra == 'test'
